spicewrapper/__init__.py
spicewrapper/data_processing.py
spicewrapper/gui.py
spicewrapper/simulation_runner.py
spicewrapper/spice_utils.py
spicewrapper/waveformeditor.py
spicewrapper/workers.py
spicewrapper-0.13.19.dist-info/LICENSE
spicewrapper-0.13.19.dist-info/METADATA
spicewrapper-0.13.19.dist-info/WHEEL
spicewrapper-0.13.19.dist-info/top_level.txt
spicewrapper-0.13.19.dist-info/RECORD
