Metadata-Version: 2.1
Name: spicewrapper
Version: 0.13.19
Summary: Tool to automate running, editing, and plotting NGSpice simulations (preview version)
Home-page: https://github.com/pseudotexan/spicewrapper
Author: jeff chiles
Author-email: pseudotexan@gmail.com
Classifier: Programming Language :: Python :: 3
Classifier: License :: OSI Approved :: MIT License
Classifier: Operating System :: OS Independent
Requires-Python: >=3.6
License-File: LICENSE
Requires-Dist: numpy
Requires-Dist: pandas
Requires-Dist: matplotlib
Requires-Dist: scipy
Requires-Dist: pyperclip
